AutoStats/__init__.py
AutoStats/impute.py
AutoStats/report.py
autostats-0.1.4.dist-info/licenses/LICENSE
autostats-0.1.4.dist-info/METADATA
autostats-0.1.4.dist-info/WHEEL
autostats-0.1.4.dist-info/top_level.txt
autostats-0.1.4.dist-info/RECORD
