Metadata-Version: 2.4
Name: AutoStats
Version: 0.1.4
Summary: A Python package for automatic statistical analysis and imputation
Home-page: https://https://github.com/iMaatin/AutoStats
Author: iMaatin
Author-email: iMaatin <2012irajpour@gmail.com>
Project-URL: Homepage, https://https://github.com/iMaatin/AutoStats
Classifier: Programming Language :: Python :: 3
Classifier: License :: OSI Approved :: MIT License
Classifier: Operating System :: OS Independent
Requires-Python: >=3.10
License-File: LICENSE
Dynamic: author
Dynamic: home-page
Dynamic: license-file
Dynamic: requires-python
